{"ddd":0,"h":517,"w":517,"layers":[{"ty":4,"sr":1,"st":0,"op":317,"ip":0,"hasMask":false,"ao":0,"ks":{"a":{"a":0,"k":[258.21,258.21,0]},"s":{"a":0,"k":[100,100]},"p":{"a":0,"k":[258.21,258.21,0]},"r":{"a":0,"k":0},"o":{"a":0,"k":100}},"shapes":[{"ty":"gr","it":[{"ty":"sh","d":1,"ks":{"a":0,"k":{"c":true,"i":[[-7.96,-7.96],[7.96,-7.96],[7.96,7.96],[-7.96,7.96]],"o":[[7.96,7.96],[-7.96,7.96],[-7.96,-7.96],[7.96,-7.96]],"v":[[14.41,-14.41],[14.41,14.41],[-14.41,14.41],[-14.41,-14.41]]}}},{"ty":"st","lc":1,"lj":1,"ml":10,"o":{"a":0,"k":100},"w":{"a":0,"k":9},"c":{"a":0,"k":[1,0.53,0]}},{"ty":"tr","a":{"a":0,"k":[0,0]},"s":{"a":0,"k":[100,100]},"p":{"a":0,"k":[150.94,365.46]},"r":{"a":0,"k":0},"o":{"a":0,"k":100}}]}],"ind":1},{"ty":4,"sr":1,"st":0,"op":317,"ip":0,"hasMask":false,"ao":0,"ks":{"a":{"a":0,"k":[258.21,258.21,0]},"s":{"a":0,"k":[100,100]},"p":{"a":0,"k":[258.21,258.21,0]},"r":{"a":0,"k":0},"o":{"a":0,"k":100}},"shapes":[{"ty":"gr","it":[{"ty":"sh","d":1,"ks":{"a":0,"k":{"c":true,"i":[[-7.96,-7.96],[7.96,-7.96],[7.96,7.96],[-7.96,7.96]],"o":[[7.96,7.96],[-7.96,7.96],[-7.96,-7.96],[7.96,-7.96]],"v":[[14.41,-14.41],[14.41,14.41],[-14.41,14.41],[-14.41,-14.41]]}}},{"ty":"st","lc":1,"lj":1,"ml":10,"o":{"a":0,"k":100},"w":{"a":0,"k":9},"c":{"a":0,"k":[1,0.53,0]}},{"ty":"tr","a":{"a":0,"k":[0,0]},"s":{"a":0,"k":[100,100]},"p":{"a":0,"k":[366.41,366.41]},"r":{"a":0,"k":0},"o":{"a":0,"k":100}}]}],"ind":2},{"ty":4,"sr":1,"st":0,"op":242,"ip":0,"hasMask":false,"ao":0,"ks":{"a":{"a":0,"k":[0,0]},"s":{"a":0,"k":[100,100]},"p":{"a":0,"k":[259,473.25,0]},"r":{"a":0,"k":0},"o":{"a":1,"k":[{"o":{"x":0.17,"y":0},"i":{"x":0.83,"y":1},"s":[12],"t":82},{"o":{"x":0.17,"y":0},"i":{"x":0.83,"y":1},"s":[100],"t":99},{"o":{"x":0.17,"y":0},"i":{"x":0.83,"y":1},"s":[100],"t":196},{"s":[2],"t":211}]}},"shapes":[{"ty":"gr","it":[{"ty":"el","d":1,"p":{"a":0,"k":[0,0]},"s":{"a":0,"k":[36.5,36.5]}},{"ty":"fl","c":{"a":0,"k":[1,0.53,0]},"r":1,"o":{"a":0,"k":99}},{"ty":"tr","a":{"a":0,"k":[0,0]},"s":{"a":0,"k":[100,100]},"p":{"a":0,"k":[-108.75,-108.5]},"r":{"a":0,"k":0},"o":{"a":0,"k":100}}]}],"ind":3,"parent":1},{"ty":4,"sr":1,"st":0,"op":242,"ip":0,"hasMask":false,"ao":0,"ks":{"a":{"a":0,"k":[0,0]},"s":{"a":0,"k":[100,100]},"p":{"a":0,"k":[474.5,475.5,0]},"r":{"a":0,"k":0},"o":{"a":1,"k":[{"o":{"x":0.17,"y":0},"i":{"x":0.83,"y":1},"s":[12],"t":60},{"o":{"x":0.17,"y":0},"i":{"x":0.83,"y":1},"s":[100],"t":77},{"o":{"x":0.17,"y":0},"i":{"x":0.83,"y":1},"s":[100],"t":196},{"s":[2],"t":211}]}},"shapes":[{"ty":"gr","it":[{"ty":"el","d":1,"p":{"a":0,"k":[0,0]},"s":{"a":0,"k":[36.5,36.5]}},{"ty":"fl","c":{"a":0,"k":[1,0.53,0]},"r":1,"o":{"a":0,"k":99}},{"ty":"tr","a":{"a":0,"k":[0,0]},"s":{"a":0,"k":[100,100]},"p":{"a":0,"k":[-108.75,-108.5]},"r":{"a":0,"k":0},"o":{"a":0,"k":100}}]}],"ind":4,"parent":2},{"ty":4,"sr":1,"st":0,"op":242,"ip":0,"hasMask":false,"ao":0,"ks":{"a":{"a":0,"k":[0,0]},"s":{"a":0,"k":[100,100]},"p":{"a":0,"k":[474.5,258.5,0]},"r":{"a":0,"k":0},"o":{"a":1,"k":[{"o":{"x":0.17,"y":0},"i":{"x":0.83,"y":1},"s":[12],"t":31},{"o":{"x":0.17,"y":0},"i":{"x":0.83,"y":1},"s":[100],"t":48},{"o":{"x":0.17,"y":0},"i":{"x":0.83,"y":1},"s":[100],"t":196},{"s":[2],"t":211}]}},"shapes":[{"ty":"gr","it":[{"ty":"el","d":1,"p":{"a":0,"k":[0,0]},"s":{"a":0,"k":[36.5,36.5]}},{"ty":"fl","c":{"a":0,"k":[1,0.53,0]},"r":1,"o":{"a":0,"k":99}},{"ty":"tr","a":{"a":0,"k":[0,0]},"s":{"a":0,"k":[100,100]},"p":{"a":0,"k":[-108.75,-108.5]},"r":{"a":0,"k":0},"o":{"a":0,"k":100}}]}],"ind":5,"parent":8},{"ty":4,"sr":1,"st":0,"op":242,"ip":0,"hasMask":false,"ao":0,"ks":{"a":{"a":0,"k":[0,0]},"s":{"a":0,"k":[100,100]},"p":{"a":0,"k":[258.5,258.5]},"r":{"a":0,"k":0},"o":{"a":1,"k":[{"o":{"x":0.33,"y":0},"i":{"x":0.67,"y":1},"s":[0],"t":0},{"o":{"x":0.17,"y":0},"i":{"x":0.83,"y":1},"s":[100],"t":18},{"o":{"x":0.17,"y":0},"i":{"x":0.83,"y":1},"s":[100],"t":196},{"s":[2],"t":211}]}},"shapes":[{"ty":"gr","it":[{"ty":"el","d":1,"p":{"a":0,"k":[0,0]},"s":{"a":0,"k":[36.5,36.5]}},{"ty":"fl","c":{"a":0,"k":[1,0.53,0]},"r":1,"o":{"a":0,"k":99}},{"ty":"tr","a":{"a":0,"k":[0,0]},"s":{"a":0,"k":[100,100]},"p":{"a":0,"k":[-108.75,-108.5]},"r":{"a":0,"k":0},"o":{"a":0,"k":100}}]}],"ind":6},{"ty":4,"sr":1,"st":0,"op":317,"ip":0,"hasMask":false,"ao":0,"ks":{"a":{"a":0,"k":[258.21,258.21,0]},"s":{"a":0,"k":[100,100]},"p":{"a":0,"k":[-0.29,-0.29,0]},"r":{"a":0,"k":0},"o":{"a":0,"k":100}},"shapes":[{"ty":"gr","it":[{"ty":"sh","d":1,"ks":{"a":0,"k":{"c":true,"i":[[-7.96,-7.96],[7.96,-7.96],[7.96,7.96],[-7.96,7.96]],"o":[[7.96,7.96],[-7.96,7.96],[-7.96,-7.96],[7.96,-7.96]],"v":[[14.41,-14.41],[14.41,14.41],[-14.41,14.41],[-14.41,-14.41]]}}},{"ty":"st","lc":1,"lj":1,"ml":10,"o":{"a":0,"k":100},"w":{"a":0,"k":9},"c":{"a":0,"k":[1,0.53,0]}},{"ty":"tr","a":{"a":0,"k":[0,0]},"s":{"a":0,"k":[100,100]},"p":{"a":0,"k":[150,150]},"r":{"a":0,"k":0},"o":{"a":0,"k":100}}]}],"ind":7,"parent":6},{"ty":4,"sr":1,"st":0,"op":317,"ip":0,"hasMask":false,"ao":0,"ks":{"a":{"a":0,"k":[258.21,258.21,0]},"s":{"a":0,"k":[100,100]},"p":{"a":0,"k":[258.21,258.21,0]},"r":{"a":0,"k":0},"o":{"a":0,"k":100}},"shapes":[{"ty":"gr","it":[{"ty":"sh","d":1,"ks":{"a":0,"k":{"c":true,"i":[[-7.96,-7.96],[7.96,-7.96],[7.96,7.96],[-7.96,7.96]],"o":[[7.96,7.96],[-7.96,7.96],[-7.96,-7.96],[7.96,-7.96]],"v":[[14.41,-14.41],[14.41,14.41],[-14.41,14.41],[-14.41,-14.41]]}}},{"ty":"st","lc":1,"lj":1,"ml":10,"o":{"a":0,"k":100},"w":{"a":0,"k":9},"c":{"a":0,"k":[1,0.53,0]}},{"ty":"tr","a":{"a":0,"k":[0,0]},"s":{"a":0,"k":[100,100]},"p":{"a":0,"k":[366.41,150]},"r":{"a":0,"k":0},"o":{"a":0,"k":100}}]}],"ind":8},{"ty":4,"sr":1,"st":0,"op":317,"ip":0,"hasMask":false,"ao":0,"ks":{"a":{"a":0,"k":[258.21,258.21,0]},"s":{"a":0,"k":[100,100]},"p":{"a":1,"k":[{"o":{"x":0.33,"y":0},"i":{"x":0.67,"y":1},"s":[258.21,256.21,0],"t":0},{"o":{"x":0.59,"y":0},"i":{"x":0.67,"y":1},"s":[250.58,251.46,0],"t":22},{"o":{"x":0.48,"y":0},"i":{"x":0.67,"y":0.96},"s":[265.83,251.71,0],"t":50.22},{"o":{"x":0.17,"y":0.01},"i":{"x":0.67,"y":0.97},"s":[266.83,266.32,0],"t":80},{"o":{"x":0.62,"y":0},"i":{"x":0.85,"y":1},"s":[248.21,266.32,0],"t":107},{"s":[258.46,256.32,0],"t":139}]},"r":{"a":0,"k":0},"o":{"a":0,"k":100}},"shapes":[{"ty":"gr","it":[{"ty":"sh","d":1,"ks":{"a":0,"k":{"c":true,"i":[[1.07,-18.34],[18.34,1.07],[-1.07,18.34],[-18.34,-1.07]],"o":[[-1.07,18.34],[-18.34,-1.07],[1.07,-18.34],[18.34,1.07]],"v":[[33.21,1.93],[-1.93,33.21],[-33.21,-1.93],[1.93,-33.21]]}}},{"ty":"st","lc":1,"lj":1,"ml":10,"o":{"a":0,"k":100},"w":{"a":0,"k":9},"c":{"a":0,"k":[1,1,1]}},{"ty":"tr","a":{"a":0,"k":[0,0]},"s":{"a":0,"k":[100,100]},"p":{"a":0,"k":[258.06,231.4]},"r":{"a":0,"k":0},"o":{"a":0,"k":100}}]}],"ind":9},{"ty":4,"sr":1,"st":0,"op":317,"ip":0,"hasMask":false,"ao":0,"ks":{"a":{"a":0,"k":[258.21,258.21,0]},"s":{"a":0,"k":[100,100]},"p":{"a":0,"k":[258.21,258.21,0]},"r":{"a":0,"k":0},"o":{"a":0,"k":100}},"shapes":[{"ty":"gr","it":[{"ty":"sh","d":1,"ks":{"a":0,"k":{"c":false,"i":[[0,0],[0,0]],"o":[[0,0],[0,0]],"v":[[14.03,-14.03],[-14.03,14.03]]}}},{"ty":"st","lc":1,"lj":1,"ml":10,"o":{"a":0,"k":100},"w":{"a":0,"k":9},"c":{"a":0,"k":[1,1,1]}},{"ty":"tr","a":{"a":0,"k":[0,0]},"s":{"a":0,"k":[100,100]},"p":{"a":0,"k":[337.98,178.44]},"r":{"a":0,"k":0},"o":{"a":0,"k":100}}]}],"ind":10},{"ty":4,"sr":1,"st":0,"op":317,"ip":0,"hasMask":false,"ao":0,"ks":{"a":{"a":0,"k":[258.21,258.21,0]},"s":{"a":0,"k":[100,100]},"p":{"a":0,"k":[258.21,258.21,0]},"r":{"a":0,"k":0},"o":{"a":0,"k":100}},"shapes":[{"ty":"gr","it":[{"ty":"sh","d":1,"ks":{"a":0,"k":{"c":false,"i":[[0,0],[0,0]],"o":[[0,0],[0,0]],"v":[[13.55,-13.55],[-13.55,13.55]]}}},{"ty":"st","lc":1,"lj":1,"ml":10,"o":{"a":0,"k":100},"w":{"a":0,"k":9},"c":{"a":0,"k":[1,1,1]}},{"ty":"tr","a":{"a":0,"k":[0,0]},"s":{"a":0,"k":[100,100]},"p":{"a":0,"k":[178.91,337.5]},"r":{"a":0,"k":0},"o":{"a":0,"k":100}}]}],"ind":11},{"ty":4,"sr":1,"st":0,"op":317,"ip":0,"hasMask":false,"ao":0,"ks":{"a":{"a":0,"k":[258.21,258.21,0]},"s":{"a":0,"k":[100,100]},"p":{"a":0,"k":[258.21,258.21,0]},"r":{"a":0,"k":0},"o":{"a":0,"k":100}},"shapes":[{"ty":"gr","it":[{"ty":"sh","d":1,"ks":{"a":0,"k":{"c":false,"i":[[0,0],[0,0]],"o":[[0,0],[0,0]],"v":[[-14.03,-14.03],[14.03,14.03]]}}},{"ty":"st","lc":1,"lj":1,"ml":10,"o":{"a":0,"k":100},"w":{"a":0,"k":9},"c":{"a":0,"k":[1,1,1]}},{"ty":"tr","a":{"a":0,"k":[0,0]},"s":{"a":0,"k":[100,100]},"p":{"a":0,"k":[178.44,178.44]},"r":{"a":0,"k":0},"o":{"a":0,"k":100}}]}],"ind":12},{"ty":4,"sr":1,"st":0,"op":317,"ip":0,"hasMask":false,"ao":0,"ks":{"a":{"a":0,"k":[258.21,258.21,0]},"s":{"a":0,"k":[100,100]},"p":{"a":0,"k":[258.21,258.21,0]},"r":{"a":0,"k":0},"o":{"a":0,"k":100}},"shapes":[{"ty":"gr","it":[{"ty":"sh","d":1,"ks":{"a":0,"k":{"c":false,"i":[[0,0],[0,0]],"o":[[0,0],[0,0]],"v":[[-14.03,-14.03],[14.03,14.03]]}}},{"ty":"st","lc":1,"lj":1,"ml":10,"o":{"a":0,"k":100},"w":{"a":0,"k":9},"c":{"a":0,"k":[1,1,1]}},{"ty":"tr","a":{"a":0,"k":[0,0]},"s":{"a":0,"k":[100,100]},"p":{"a":0,"k":[337.98,337.98]},"r":{"a":0,"k":0},"o":{"a":0,"k":100}}]}],"ind":13},{"ty":4,"sr":1,"st":0,"op":317,"ip":0,"hasMask":false,"ao":0,"ks":{"a":{"a":0,"k":[258.21,258.21,0]},"s":{"a":0,"k":[113.01,100,100]},"p":{"a":1,"k":[{"o":{"x":0,"y":0},"i":{"x":0.67,"y":1},"s":[258.21,256.21,0],"t":0},{"o":{"x":0.33,"y":0.33},"i":{"x":0.67,"y":0.67},"s":[258.21,248.71,0],"t":22},{"o":{"x":0.48,"y":0},"i":{"x":0.33,"y":1},"s":[258.21,248.71,0],"t":51},{"o":{"x":0.33,"y":0.33},"i":{"x":1,"y":1},"s":[258.21,256.21,0],"t":88},{"s":[258.21,256.21,0],"t":107}]},"r":{"a":0,"k":0},"o":{"a":0,"k":100}},"shapes":[{"ty":"gr","it":[{"ty":"sh","d":1,"ks":{"a":0,"k":{"c":true,"i":[[0,0],[-23.44,0],[0,-23.44]],"o":[[0,-23.44],[23.44,0],[0,0]],"v":[[-42.43,21.22],[0,-21.22],[42.43,21.22]]}}},{"ty":"st","lc":1,"lj":1,"ml":10,"o":{"a":0,"k":100},"w":{"a":0,"k":9},"c":{"a":0,"k":[1,1,1]}},{"ty":"tr","a":{"a":0,"k":[0,0]},"s":{"a":0,"k":[100,100]},"p":{"a":0,"k":[258.06,287.28]},"r":{"a":0,"k":0},"o":{"a":0,"k":100}}]}],"ind":14},{"ty":4,"sr":1,"st":0,"op":317,"ip":0,"hasMask":false,"ao":0,"ks":{"a":{"a":0,"k":[258.21,258.21,0]},"s":{"a":0,"k":[100,100]},"p":{"a":0,"k":[258.21,258.21,0]},"r":{"a":0,"k":0},"o":{"a":0,"k":100}},"shapes":[{"ty":"gr","it":[{"ty":"sh","d":1,"ks":{"a":0,"k":{"c":true,"i":[[0,-51.35],[51.35,0],[0,51.35],[-51.35,0]],"o":[[0,51.35],[-51.35,0],[0,-51.35],[51.35,0]],"v":[[92.97,0],[0,92.97],[-92.97,0],[0,-92.97]]}}},{"ty":"st","lc":1,"lj":1,"ml":10,"o":{"a":0,"k":100},"w":{"a":0,"k":9},"c":{"a":0,"k":[1,1,1]}},{"ty":"tr","a":{"a":0,"k":[0,0]},"s":{"a":0,"k":[100,100]},"p":{"a":0,"k":[258.21,258.21]},"r":{"a":0,"k":0},"o":{"a":0,"k":100}}]}],"ind":15}],"v":"5.7.0","fr":60,"op":242,"ip":0,"assets":[]}